bizhi_framework/__init__.py
bizhi_framework/app_encrypt.py
bizhi_framework/bd_censor.py
bizhi_framework/bd_login.py
bizhi_framework/file_upload.py
bizhi_framework/useranget.py
bizhi_framework/wallpaper_elasticsearch.py
bizhi_framework/wallpaper_memcache.py
bizhi_framework/wallpaper_redis.py
bizhi_framework/bizhi_web/__init__.py
bizhi_framework/bizhi_web/bizhi_base_handler.py
bizhi_framework/bizhi_web/useragent.py
bizhi_framework-1.0.17.dist-info/METADATA
bizhi_framework-1.0.17.dist-info/WHEEL
bizhi_framework-1.0.17.dist-info/top_level.txt
bizhi_framework-1.0.17.dist-info/RECORD
