Metadata-Version: 2.1
Name: bizhi-framework
Version: 1.0.17
Summary: bizhi project base framework
Home-page: UNKNOWN
Author: huangwenbin
Author-email: UNKNOWN
License: UNKNOWN
Platform: UNKNOWN
Requires-Dist: seven-framework >=1.1.32
